{
	"Competitve Programming/ OOP": {
		"prefix": "javahack",
		"body": [
			"import java.io.*;",
			"import java.util.*;",
			"import java.lang.Math.*;",
			"",
			"public class  {",
			"    public static void main(String[] args) throws IOException {",
			"        File inputFile = new File(\"E:/OneDrive - ptit.edu.vn/pro/dsa/input.txt\");",
			"        if (inputFile.exists()) {",
			"            System.setIn(new FileInputStream(\"E:/OneDrive - ptit.edu.vn/pro/dsa/input.txt\"));",
			"            System.setOut(new PrintStream(\"E:/OneDrive - ptit.edu.vn/pro/dsa/output.txt\"));",
			"        }",
			"        FastScanner sc = new FastScanner();",
			"",
			"        int t = sc.nint();",
			"        while (t-- > 0) {",
			"            int n = sc.nint();",
			"            int a[] = sc.aint();",
			"",
			"        }",
			"    }",
			"",
			"    static class FastScanner {",
			"        private final BufferedReader br;",
			"        private StringTokenizer st = new StringTokenizer(\"\");",
			"",
			"        FastScanner(InputStream in) {",
			"            this.br = new BufferedReader(new InputStreamReader(in));",
			"        }",
			"",
			"        FastScanner() { this(System.in); }",
			"",
			"        String next() {",
			"            if (!hasNext()) throw new NoSuchElementException();",
			"            return st.nextToken();",
			"        }",
			"",
			"        int nint() { return Integer.parseInt(next()); }",
			"        long lint() { return Long.parseLong(next());}",
			"        double dint() { return Double.parseDouble(next()); }",
			"",
			"        String readline() {",
			"            String s = \"\";",
			"            try {",
			"                String t = br.readLine();",
			"                s = (t == null) ? \"\" : t.trim();",
			"            } catch (IOException e) {}",
			"            return s;",
			"        }",
			"",
			"        int[] aint() {",
			"            String s = readline();",
			"            if (s.isEmpty()) return new int[0];",
			"            return Arrays.stream(s.split(\"\\\\\\s+\")).mapToInt(Integer::parseInt).toArray();",
			"        }",
			"",
			"        boolean hasNext() {",
			"            if (st.hasMoreTokens()) return true;",
			"            try {",
			"                String line;",
			"                while ((line = br.readLine()) != null) {",
			"                    // normalize: split by non-alphanumeric",
			"                    line = line.replaceAll(\"[^A-Za-z0-9]+\", \" \");",
			"                    st = new StringTokenizer(line);",
			"                    if (st.hasMoreTokens()) return true;",
			"                }",
			"            } catch (IOException e) {",
			"                return false;",
			"            }",
			"            return false;",
			"        }",
			"    }",
			"}"
		],
		"description": "paste this at your own java.json"
	},
	"Simple for OOP": {
		"prefix": "java",
		"body": [
			"import java.io.*;",
			"import java.util.*;",
			"",
			"public class  {",
			"    public static void main(String[] args) throws IOException {",
			"        File inputFile = new File(\"E:/OneDrive - ptit.edu.vn/pro/dsa/input.txt\");",
			"        if (inputFile.exists()) {",
			"            System.setIn(new FileInputStream(inputFile));",
			"            System.setOut(new PrintStream(\"E:/OneDrive - ptit.edu.vn/pro/dsa/output.txt\"));",
			"        }",
			"        Scanner sc = new Scanner(System.in);",
			"",
			"        int t = sc.nextInt();",
			"        while (t-- > 0) {",
			"            int n = sc.nextInt();",
			"            int[] a = new int[n];",
			"            for (int i = 0; i < n; i++) {",
			"                a[i] = sc.nextInt();",
			"            }",
			"",
			"        }",
			"        sc.close();",
			"    }",
			"}"
		],
		"description": "paste this at your own java.json"
	},
	"File I/O": {
		"prefix": "fileio",
		"body": [
			"import java.io.*;",
			"import java.util.*;",
			"",
			"public class  {",
			"    public static void main(String[] args) throws IOException {",
			"        File inputFile = new File(\"E:/OneDrive - ptit.edu.vn/pro/dsa/input.txt\");",
			"        if (inputFile.exists()) {",
			"            System.setIn(new FileInputStream(inputFile));",
			"            System.setOut(new PrintStream(\"E:/OneDrive - ptit.edu.vn/pro/dsa/output.txt\"));",
			"        }",
			"        Scanner sc = new Scanner(System.in);",
			"",
			"    }",
			"}"
		],
		"description": "paste this at your own java.json"
	}
}